LingyuQudongShejiFix1/README.md
LingyuQudongShejiFix1/__init__.py
LingyuQudongShejiFix1/__main__.py
LingyuQudongShejiFix1/file.epub
LingyuQudongShejiFix1/index.html
LingyuQudongShejiFix1/css/__init__.py
LingyuQudongShejiFix1/css/annotations.css
LingyuQudongShejiFix1/css/main.css
LingyuQudongShejiFix1/css/normalize.css
LingyuQudongShejiFix1/css/popup.css
LingyuQudongShejiFix1/font/__init__.py
LingyuQudongShejiFix1/font/fontello.eot
LingyuQudongShejiFix1/font/fontello.svg
LingyuQudongShejiFix1/font/fontello.ttf
LingyuQudongShejiFix1/font/fontello.woff
LingyuQudongShejiFix1/img/__init__.py
LingyuQudongShejiFix1/img/annotator-glyph-sprite.png
LingyuQudongShejiFix1/img/annotator-icon-sprite.png
LingyuQudongShejiFix1/img/apple-touch-icon.png
LingyuQudongShejiFix1/img/cancelfullscreen.png
LingyuQudongShejiFix1/img/close.png
LingyuQudongShejiFix1/img/fullscreen.png
LingyuQudongShejiFix1/img/loader.gif
LingyuQudongShejiFix1/img/menu-icon.png
LingyuQudongShejiFix1/img/save.png
LingyuQudongShejiFix1/img/saved.png
LingyuQudongShejiFix1/img/settings-s.png
LingyuQudongShejiFix1/img/settings.png
LingyuQudongShejiFix1/img/star.png
LingyuQudongShejiFix1/js/__init__.py
LingyuQudongShejiFix1/js/epub.js
LingyuQudongShejiFix1/js/epub.min.js
LingyuQudongShejiFix1/js/epub.min.map
LingyuQudongShejiFix1/js/hooks.min.js
LingyuQudongShejiFix1/js/hooks.min.map
LingyuQudongShejiFix1/js/reader.js
LingyuQudongShejiFix1/js/reader.js.map
LingyuQudongShejiFix1/js/reader.min.js
LingyuQudongShejiFix1/js/reader.min.map
LingyuQudongShejiFix1/js/hooks/__init__.py
LingyuQudongShejiFix1/js/hooks/extensions/__init__.py
LingyuQudongShejiFix1/js/hooks/extensions/highlight.js
LingyuQudongShejiFix1/js/libs/__init__.py
LingyuQudongShejiFix1/js/libs/jquery.min.js
LingyuQudongShejiFix1/js/libs/localforage.min.js
LingyuQudongShejiFix1/js/libs/screenfull.js
LingyuQudongShejiFix1/js/libs/screenfull.min.js
LingyuQudongShejiFix1/js/libs/zip.min.js
LingyuQudongShejiFix1/js/plugins/__init__.py
lingyu_qudong_sheji_fix1-2025.3.24.0.dist-info/METADATA
lingyu_qudong_sheji_fix1-2025.3.24.0.dist-info/WHEEL
lingyu_qudong_sheji_fix1-2025.3.24.0.dist-info/entry_points.txt
lingyu_qudong_sheji_fix1-2025.3.24.0.dist-info/top_level.txt
lingyu_qudong_sheji_fix1-2025.3.24.0.dist-info/RECORD
